MANIFEST.in
README.rst
requirements-dev.txt
requirements-test.txt
setup.py
django_generic_tagging.egg-info/PKG-INFO
django_generic_tagging.egg-info/SOURCES.txt
django_generic_tagging.egg-info/dependency_links.txt
django_generic_tagging.egg-info/not-zip-safe
django_generic_tagging.egg-info/top_level.txt
generic_tagging/__init__.py
generic_tagging/compatibility.py
generic_tagging/exceptions.py
generic_tagging/models.py
generic_tagging/urls.py
generic_tagging/views.py
generic_tagging/api/__init__.py
generic_tagging/api/fields.py
generic_tagging/api/routers.py
generic_tagging/api/serializers.py
generic_tagging/api/viewsets.py
generic_tagging/migrations/0001_initial.py
generic_tagging/migrations/__init__.py
generic_tagging/static/generic_tagging/css/generic-tagging.css
generic_tagging/static/generic_tagging/css/images/sprites.png
generic_tagging/static/generic_tagging/css/images/tag.png
generic_tagging/static/generic_tagging/javascript/generic-tagging.js
generic_tagging/templates/generic_tagging/component.html
generic_tagging/templates/generic_tagging/head.html
generic_tagging/templatetags/__init__.py
generic_tagging/templatetags/tagging.py
generic_tagging/tests/__init__.py
generic_tagging/tests/compatibility.py
generic_tagging/tests/factories.py
generic_tagging/tests/models.py
generic_tagging/tests/test_managers.py
generic_tagging/tests/test_models.py
generic_tagging/tests/test_templatetags.py
generic_tagging/tests/test_views.py
generic_tagging/tests/test_api/__init__.py
generic_tagging/tests/test_api/test_serializers.py
generic_tagging/tests/test_api/test_viewsets.py
tests/__init__.py
tests/settings.py
tests/urls.py