Metadata-Version: 1.1
Name: django-generic-tagging
Version: 0.0.2
Summary: A generic tagging plugin for Django
Home-page: https://github.com/giginet/django-generic-tagging
Author: giginet
Author-email: giginet.net@gmail.com
License: MIT
Download-URL: https://github.com/giginet/django-generic-tagging/tarball/master
Keywords: django tagging tag
Platform: UNKNOWN
Classifier: Development Status :: 5 - Production/Stable
Classifier: Environment :: Web Environment
Classifier: Framework :: Django
Classifier: Intended Audience :: Developers
Classifier: License :: OSI Approved :: MIT License
Classifier: Programming Language :: Python
Classifier: Programming Language :: Python :: 3
Classifier: Programming Language :: Python :: 3.3
Classifier: Programming Language :: Python :: 3.4
Classifier: Programming Language :: Python :: 3.5
Classifier: Topic :: Internet :: WWW/HTTP
Classifier: Topic :: Software Development :: Libraries
Classifier: Topic :: Software Development :: Libraries :: Application Frameworks
Classifier: Topic :: Software Development :: Libraries :: Python Modules
